{
  "book": "John",
  "chapter": "18",
  "date": "Tuesday 28-May, 2024",
  "getbible": "https://getbible.net/kjv/John/18/20",
  "name": "John 18:20",
  "scripture": [
    {
      "nr": "20",
      "text": "Jesus answered him, I spake openly to the world; I ever taught in the synagogue, and in the temple, whither the Jews always resort; and in secret have I said nothing."
    }
  ],
  "source": "https://git.vdm.dev/christian/daily-scripture",
  "telegram": "daily_scripture",
  "verse": "20",
  "version": "kjv"
}
