{
  "book": "Isaiah",
  "chapter": "62",
  "date": "Saturday 20-September, 2025",
  "getbible": "https://getbible.life/kjv/Isaiah/62/1",
  "name": "Isaiah 62:1",
  "scripture": [
    {
      "nr": "1",
      "text": "For Zion’s sake will I not hold my peace, and for Jerusalem’s sake I will not rest, until the righteousness thereof go forth as brightness, and the salvation thereof as a lamp that burneth."
    }
  ],
  "source": "https://git.vdm.dev/christian/daily-scripture",
  "telegram": "daily_scripture",
  "verse": "1",
  "version": "kjv"
}
