{
  "book": "1 Corinthians",
  "chapter": "10",
  "date": "Friday 08-November, 2024",
  "getbible": "https://getbible.life/kjv/1 Corinthians/10/23",
  "name": "1 Corinthians 10:23",
  "scripture": [
    {
      "nr": "23",
      "text": "All things are lawful for me, but all things are not expedient: all things are lawful for me, but all things edify not."
    }
  ],
  "source": "https://git.vdm.dev/christian/daily-scripture",
  "telegram": "daily_scripture",
  "verse": "23",
  "version": "kjv"
}
