{
  "book": "John",
  "chapter": "16",
  "date": "Friday 29-March, 2024",
  "getbible": "https://getbible.life/kjv/John/16/21",
  "name": "John 16:21",
  "scripture": [
    {
      "nr": "21",
      "text": "A woman when she is in travail hath sorrow, because her hour is come: but as soon as she is delivered of the child, she remembereth no more the anguish, for joy that a man is born into the world."
    }
  ],
  "source": "https://git.vdm.dev/christian/daily-scripture",
  "telegram": "daily_scripture",
  "verse": "21",
  "version": "kjv"
}
